{
  "type": "minecraft:generic",
  "random_sequence": "manic:gameplay/suspicious_soul_sand",
  "pools": [
    {
      "rolls": 1,
      "entries": [
        {
          "type": "minecraft:loot_table",
          "weight": 5,
          "name": "manic:items/grimstone_chunk"
        },
        {
          "type": "minecraft:loot_table",
          "weight": 5,
          "name": "manic:items/grim_quill"
        },
        {
          "type": "minecraft:loot_table",
          "weight": 5,
          "name": "manic:items/grim_rune"
        },
        {
          "type": "minecraft:loot_table",
          "weight": 30,
          "name": "manic:items/necroplasm"
        },
        {
          "type": "minecraft:item",
          "weight": 30,
          "name": "minecraft:phantom_membrane"
        },
        {
          "type": "minecraft:loot_table",
          "weight": 20,
          "name": "manic:items/moonstone"
        },
        {
          "type": "minecraft:loot_table",
          "weight": 20,
          "name": "manic:items/sunstone"
        },
        {
          "type": "minecraft:item",
          "weight": 40,
          "name": "minecraft:rotten_flesh"
        },
        {
          "type": "minecraft:item",
          "weight": 40,
          "name": "minecraft:bone"
        },
        {
          "type": "minecraft:item",
          "weight": 40,
          "name": "minecraft:bone_meal"
        },
        {
          "type": "minecraft:item",
          "weight": 20,
          "name": "minecraft:bone_block"
        },
        {
          "type": "minecraft:item",
          "weight": 40,
          "name": "minecraft:iron_ingot"
        },
        {
          "type": "minecraft:item",
          "weight": 1,
          "name": "minecraft:skeleton_skull"
        },
        {
          "type": "minecraft:item",
          "weight": 5,
          "name": "minecraft:soul_torch"
        }
      ]
    }
  ]
}
