{
  "type": "minecraft:entity",
  "pools": [
    {
      "rolls": 1,
      "entries": [
        {
          "type": "minecraft:loot_table",
          "name": "manic:items/occult_veil/heretic"
        }
      ]
    },
    {
      "rolls": 1,
      "entries": [
        {
          "type": "minecraft:item",
          "name": "minecraft:structure_block",
          "functions": [
            {
              "function": "minecraft:set_nbt",
              "tag": "{CustomModelData:8360000,nucleus:{id:\"death_item\",xp:4},manic:{entity:\"heretic\"}}"
            }
          ],
          "conditions": [
            {
              "condition": "minecraft:inverted",
              "term": {
                "condition": "minecraft:entity_properties",
                "entity": "killer",
                "predicate": {
                  "type": "minecraft:wolf"
                }
              }
            },
            {
              "condition": "minecraft:killed_by_player"
            }
          ]
        }
      ]
    }
  ]
}
